anydockerizer/__init__.py
anydockerizer/anydockerizer.py
anydockerizer/cli.py
tests/__init__.py
anydockerizer-0.0.3.dist-info/LICENSE
anydockerizer-0.0.3.dist-info/METADATA
anydockerizer-0.0.3.dist-info/WHEEL
anydockerizer-0.0.3.dist-info/entry_points.txt
anydockerizer-0.0.3.dist-info/top_level.txt
anydockerizer-0.0.3.dist-info/RECORD
